[
    {
        "username": "Alvaro.Videla",
        "photoId": "1384",
        "firstName": "Alvaro",
        "lastName": "Videla",
        "email": "alvaro.videla@fauna.com",
        "password": null,
        "admin": "0",
        "locked": "0",
        "suspended": "1",
        "pending": "0",
        "lastLoginDate": null,
        "invalidLoginCount": null,
        "lastInvalidLoginDate": null,
        "lockoutDate": null,
        "hasDashboard": "0",
        "passwordResetRequired": false,
        "lastPasswordChangeDate": null,
        "unverifiedEmail": null,
        "newPassword": null,
        "currentPassword": null,
        "verificationCodeIssuedDate": null,
        "verificationCode": null,
        "lastLoginAttemptIp": null,
        "authError": null,
        "inheritorOnDelete": null,
        "id": 1383,
        "tempId": null,
        "draftId": null,
        "revisionId": null,
        "uid": "07736d41-4e1c-497f-a805-9d926a2d9834",
        "siteSettingsId": 1383,
        "fieldLayoutId": null,
        "contentId": 1047,
        "enabled": true,
        "archived": false,
        "siteId": 1,
        "title": null,
        "slug": null,
        "uri": null,
        "dateCreated": "2018-09-25T08:24:19-07:00",
        "dateUpdated": "2019-07-16T12:47:23-07:00",
        "dateDeleted": null,
        "trashed": false,
        "propagateAll": false,
        "newSiteIds": [],
        "resaving": false,
        "duplicateOf": null,
        "previewing": false,
        "hardDelete": false,
        "ref": "Alvaro.Videla",
        "status": "suspended",
        "structureId": null,
        "url": null,
        "cooldownEndTime": null,
        "friendlyName": "Alvaro",
        "fullName": "Alvaro Videla",
        "isCurrent": false,
        "name": "Alvaro Videla",
        "preferredLanguage": null,
        "remainingCooldownTime": null
    },
    {
        "username": "amnapervez",
        "photoId": null,
        "firstName": "Amna",
        "lastName": "Pervez",
        "email": "amna@fauna.com",
        "password": null,
        "admin": "0",
        "locked": "0",
        "suspended": "1",
        "pending": "1",
        "lastLoginDate": null,
        "invalidLoginCount": null,
        "lastInvalidLoginDate": null,
        "lockoutDate": null,
        "hasDashboard": "0",
        "passwordResetRequired": false,
        "lastPasswordChangeDate": null,
        "unverifiedEmail": null,
        "newPassword": null,
        "currentPassword": null,
        "verificationCodeIssuedDate": null,
        "verificationCode": null,
        "lastLoginAttemptIp": null,
        "authError": null,
        "inheritorOnDelete": null,
        "id": 469,
        "tempId": null,
        "draftId": null,
        "revisionId": null,
        "uid": "80bb3dba-813a-4bf2-a76f-3854439f87fd",
        "siteSettingsId": 469,
        "fieldLayoutId": null,
        "contentId": 302,
        "enabled": true,
        "archived": false,
        "siteId": 1,
        "title": null,
        "slug": null,
        "uri": null,
        "dateCreated": "2018-08-27T05:12:23-07:00",
        "dateUpdated": "2018-09-20T21:48:09-07:00",
        "dateDeleted": null,
        "trashed": false,
        "propagateAll": false,
        "newSiteIds": [],
        "resaving": false,
        "duplicateOf": null,
        "previewing": false,
        "hardDelete": false,
        "ref": "amnapervez",
        "status": "suspended",
        "structureId": null,
        "url": null,
        "cooldownEndTime": null,
        "friendlyName": "Amna",
        "fullName": "Amna Pervez",
        "isCurrent": false,
        "name": "Amna Pervez",
        "preferredLanguage": null,
        "remainingCooldownTime": null
    },
    {
        "username": "AnthonyCampolo",
        "photoId": null,
        "firstName": "Anthony",
        "lastName": "Campolo",
        "email": "anthonycampolo@fauna.com",
        "password": null,
        "admin": "0",
        "locked": "0",
        "suspended": "0",
        "pending": "0",
        "lastLoginDate": null,
        "invalidLoginCount": null,
        "lastInvalidLoginDate": null,
        "lockoutDate": null,
        "hasDashboard": "0",
        "passwordResetRequired": false,
        "lastPasswordChangeDate": null,
        "unverifiedEmail": null,
        "newPassword": null,
        "currentPassword": null,
        "verificationCodeIssuedDate": null,
        "verificationCode": null,
        "lastLoginAttemptIp": null,
        "authError": null,
        "inheritorOnDelete": null,
        "id": 8698,
        "tempId": null,
        "draftId": null,
        "revisionId": null,
        "uid": "169ae96d-a332-4b9f-b83f-5b3db995cd62",
        "siteSettingsId": 8698,
        "fieldLayoutId": null,
        "contentId": 2949,
        "enabled": true,
        "archived": false,
        "siteId": 1,
        "title": null,
        "slug": null,
        "uri": null,
        "dateCreated": "2020-08-28T13:08:47-07:00",
        "dateUpdated": "2020-08-28T13:08:47-07:00",
        "dateDeleted": null,
        "trashed": false,
        "propagateAll": false,
        "newSiteIds": [],
        "resaving": false,
        "duplicateOf": null,
        "previewing": false,
        "hardDelete": false,
        "ref": "AnthonyCampolo",
        "status": "active",
        "structureId": null,
        "url": null,
        "cooldownEndTime": null,
        "friendlyName": "Anthony",
        "fullName": "Anthony Campolo",
        "isCurrent": false,
        "name": "Anthony Campolo",
        "preferredLanguage": null,
        "remainingCooldownTime": null
    },
    {
        "username": "Artur-Tomusiak",
        "photoId": null,
        "firstName": "Artur",
        "lastName": "Tomusiak",
        "email": "Artur-Tomusiak@fauna.com",
        "password": null,
        "admin": "0",
        "locked": "0",
        "suspended": "0",
        "pending": "0",
        "lastLoginDate": null,
        "invalidLoginCount": null,
        "lastInvalidLoginDate": null,
        "lockoutDate": null,
        "hasDashboard": "0",
        "passwordResetRequired": false,
        "lastPasswordChangeDate": null,
        "unverifiedEmail": null,
        "newPassword": null,
        "currentPassword": null,
        "verificationCodeIssuedDate": null,
        "verificationCode": null,
        "lastLoginAttemptIp": null,
        "authError": null,
        "inheritorOnDelete": null,
        "id": 8494,
        "tempId": null,
        "draftId": null,
        "revisionId": null,
        "uid": "49fbe9fc-430b-4277-a63f-9fb5ef1bb408",
        "siteSettingsId": 8494,
        "fieldLayoutId": null,
        "contentId": 2840,
        "enabled": true,
        "archived": false,
        "siteId": 1,
        "title": null,
        "slug": null,
        "uri": null,
        "dateCreated": "2020-07-08T14:57:21-07:00",
        "dateUpdated": "2020-07-08T14:57:21-07:00",
        "dateDeleted": null,
        "trashed": false,
        "propagateAll": false,
        "newSiteIds": [],
        "resaving": false,
        "duplicateOf": null,
        "previewing": false,
        "hardDelete": false,
        "ref": "Artur-Tomusiak",
        "status": "active",
        "structureId": null,
        "url": null,
        "cooldownEndTime": null,
        "friendlyName": "Artur",
        "fullName": "Artur Tomusiak",
        "isCurrent": false,
        "name": "Artur Tomusiak",
        "preferredLanguage": null,
        "remainingCooldownTime": null
    },
    {
        "username": "BenEdwards",
        "photoId": null,
        "firstName": "Ben",
        "lastName": "Edwards",
        "email": "ben@fauna.com",
        "password": null,
        "admin": "0",
        "locked": "0",
        "suspended": "0",
        "pending": "0",
        "lastLoginDate": null,
        "invalidLoginCount": null,
        "lastInvalidLoginDate": null,
        "lockoutDate": null,
        "hasDashboard": "0",
        "passwordResetRequired": false,
        "lastPasswordChangeDate": null,
        "unverifiedEmail": null,
        "newPassword": null,
        "currentPassword": null,
        "verificationCodeIssuedDate": null,
        "verificationCode": null,
        "lastLoginAttemptIp": null,
        "authError": null,
        "inheritorOnDelete": null,
        "id": 7580,
        "tempId": null,
        "draftId": null,
        "revisionId": null,
        "uid": "6e7a1e7b-4127-4fae-8d8b-4dd0f639df0e",
        "siteSettingsId": 7580,
        "fieldLayoutId": null,
        "contentId": 2592,
        "enabled": true,
        "archived": false,
        "siteId": 1,
        "title": null,
        "slug": null,
        "uri": null,
        "dateCreated": "2020-06-19T08:07:22-07:00",
        "dateUpdated": "2020-06-19T08:07:22-07:00",
        "dateDeleted": null,
        "trashed": false,
        "propagateAll": false,
        "newSiteIds": [],
        "resaving": false,
        "duplicateOf": null,
        "previewing": false,
        "hardDelete": false,
        "ref": "BenEdwards",
        "status": "active",
        "structureId": null,
        "url": null,
        "cooldownEndTime": null,
        "friendlyName": "Ben",
        "fullName": "Ben Edwards",
        "isCurrent": false,
        "name": "Ben Edwards",
        "preferredLanguage": null,
        "remainingCooldownTime": null
    },
    {
        "username": "benjamin.weinstein",
        "photoId": null,
        "firstName": "Ben",
        "lastName": "Weinstein",
        "email": "benjamin.weinstein@fauna.com",
        "password": null,
        "admin": "1",
        "locked": "0",
        "suspended": "0",
        "pending": "0",
        "lastLoginDate": "2020-10-19T14:19:19-07:00",
        "invalidLoginCount": null,
        "lastInvalidLoginDate": null,
        "lockoutDate": null,
        "hasDashboard": "1",
        "passwordResetRequired": false,
        "lastPasswordChangeDate": null,
        "unverifiedEmail": null,
        "newPassword": null,
        "currentPassword": null,
        "verificationCodeIssuedDate": null,
        "verificationCode": null,
        "lastLoginAttemptIp": null,
        "authError": null,
        "inheritorOnDelete": null,
        "id": 1609,
        "tempId": null,
        "draftId": null,
        "revisionId": null,
        "uid": "ece6925e-7c36-4da3-bd10-b3dc7cd60a9b",
        "siteSettingsId": 1609,
        "fieldLayoutId": null,
        "contentId": 1210,
        "enabled": true,
        "archived": false,
        "siteId": 1,
        "title": null,
        "slug": null,
        "uri": null,
        "dateCreated": "2019-01-24T16:52:24-08:00",
        "dateUpdated": "2019-01-24T16:55:17-08:00",
        "dateDeleted": null,
        "trashed": false,
        "propagateAll": false,
        "newSiteIds": [],
        "resaving": false,
        "duplicateOf": null,
        "previewing": false,
        "hardDelete": false,
        "ref": "benjamin.weinstein",
        "status": "active",
        "structureId": null,
        "url": null,
        "cooldownEndTime": null,
        "friendlyName": "Ben",
        "fullName": "Ben Weinstein",
        "isCurrent": false,
        "name": "Ben Weinstein",
        "preferredLanguage": null,
        "remainingCooldownTime": null
    },
    {
        "username": "brecht.derooms",
        "photoId": null,
        "firstName": "Brecht",
        "lastName": "DeRooms",
        "email": "brecht.derooms@fauna.com",
        "password": null,
        "admin": "1",
        "locked": "0",
        "suspended": "0",
        "pending": "0",
        "lastLoginDate": "2020-10-07T08:12:34-07:00",
        "invalidLoginCount": null,
        "lastInvalidLoginDate": null,
        "lockoutDate": null,
        "hasDashboard": "1",
        "passwordResetRequired": false,
        "lastPasswordChangeDate": null,
        "unverifiedEmail": null,
        "newPassword": null,
        "currentPassword": null,
        "verificationCodeIssuedDate": null,
        "verificationCode": null,
        "lastLoginAttemptIp": null,
        "authError": null,
        "inheritorOnDelete": null,
        "id": 6380,
        "tempId": null,
        "draftId": null,
        "revisionId": null,
        "uid": "44d74cb0-0da3-4132-b36b-49e2f33ca5cb",
        "siteSettingsId": 6380,
        "fieldLayoutId": null,
        "contentId": 2174,
        "enabled": true,
        "archived": false,
        "siteId": 1,
        "title": null,
        "slug": null,
        "uri": null,
        "dateCreated": "2019-10-30T10:33:31-07:00",
        "dateUpdated": "2019-10-31T08:27:15-07:00",
        "dateDeleted": null,
        "trashed": false,
        "propagateAll": false,
        "newSiteIds": [],
        "resaving": false,
        "duplicateOf": null,
        "previewing": false,
        "hardDelete": false,
        "ref": "brecht.derooms",
        "status": "active",
        "structureId": null,
        "url": null,
        "cooldownEndTime": null,
        "friendlyName": "Brecht",
        "fullName": "Brecht DeRooms",
        "isCurrent": false,
        "name": "Brecht DeRooms",
        "preferredLanguage": null,
        "remainingCooldownTime": null
    },
    {
        "username": "BrunoQuaresma",
        "photoId": null,
        "firstName": "Bruno",
        "lastName": "Quaresma",
        "email": "bruno.quaresma@fauna.com",
        "password": null,
        "admin": "0",
        "locked": "0",
        "suspended": "0",
        "pending": "0",
        "lastLoginDate": null,
        "invalidLoginCount": null,
        "lastInvalidLoginDate": null,
        "lockoutDate": null,
        "hasDashboard": "0",
        "passwordResetRequired": false,
        "lastPasswordChangeDate": null,
        "unverifiedEmail": null,
        "newPassword": null,
        "currentPassword": null,
        "verificationCodeIssuedDate": null,
        "verificationCode": null,
        "lastLoginAttemptIp": null,
        "authError": null,
        "inheritorOnDelete": null,
        "id": 5049,
        "tempId": null,
        "draftId": null,
        "revisionId": null,
        "uid": "78ee3d9e-5f54-435e-81cc-0f62fc348f4d",
        "siteSettingsId": 5049,
        "fieldLayoutId": null,
        "contentId": 1842,
        "enabled": true,
        "archived": false,
        "siteId": 1,
        "title": null,
        "slug": null,
        "uri": null,
        "dateCreated": "2019-08-16T09:11:01-07:00",
        "dateUpdated": "2019-08-16T09:11:01-07:00",
        "dateDeleted": null,
        "trashed": false,
        "propagateAll": false,
        "newSiteIds": [],
        "resaving": false,
        "duplicateOf": null,
        "previewing": false,
        "hardDelete": false,
        "ref": "BrunoQuaresma",
        "status": "active",
        "structureId": null,
        "url": null,
        "cooldownEndTime": null,
        "friendlyName": "Bruno",
        "fullName": "Bruno Quaresma",
        "isCurrent": false,
        "name": "Bruno Quaresma",
        "preferredLanguage": null,
        "remainingCooldownTime": null
    },
    {
        "username": "cbourgeois",
        "photoId": "1366",
        "firstName": "Cary",
        "lastName": "Bourgeois",
        "email": "cbourgeois@fauna.com",
        "password": null,
        "admin": "0",
        "locked": "0",
        "suspended": "1",
        "pending": "0",
        "lastLoginDate": null,
        "invalidLoginCount": null,
        "lastInvalidLoginDate": null,
        "lockoutDate": null,
        "hasDashboard": "0",
        "passwordResetRequired": false,
        "lastPasswordChangeDate": null,
        "unverifiedEmail": null,
        "newPassword": null,
        "currentPassword": null,
        "verificationCodeIssuedDate": null,
        "verificationCode": null,
        "lastLoginAttemptIp": null,
        "authError": null,
        "inheritorOnDelete": null,
        "id": 470,
        "tempId": null,
        "draftId": null,
        "revisionId": null,
        "uid": "8826e967-9327-43c2-89d3-e8dcb0ceda02",
        "siteSettingsId": 470,
        "fieldLayoutId": null,
        "contentId": 303,
        "enabled": true,
        "archived": false,
        "siteId": 1,
        "title": null,
        "slug": null,
        "uri": null,
        "dateCreated": "2018-08-27T05:12:51-07:00",
        "dateUpdated": "2018-09-20T09:46:13-07:00",
        "dateDeleted": null,
        "trashed": false,
        "propagateAll": false,
        "newSiteIds": [],
        "resaving": false,
        "duplicateOf": null,
        "previewing": false,
        "hardDelete": false,
        "ref": "cbourgeois",
        "status": "suspended",
        "structureId": null,
        "url": null,
        "cooldownEndTime": null,
        "friendlyName": "Cary",
        "fullName": "Cary Bourgeois",
        "isCurrent": false,
        "name": "Cary Bourgeois",
        "preferredLanguage": null,
        "remainingCooldownTime": null
    },
    {
        "username": "chrisanderson",
        "photoId": "535",
        "firstName": "Chris",
        "lastName": "Anderson",
        "email": "chris@fauna.com",
        "password": null,
        "admin": "1",
        "locked": "0",
        "suspended": "1",
        "pending": "0",
        "lastLoginDate": "2019-06-25T12:04:19-07:00",
        "invalidLoginCount": null,
        "lastInvalidLoginDate": null,
        "lockoutDate": null,
        "hasDashboard": "1",
        "passwordResetRequired": false,
        "lastPasswordChangeDate": null,
        "unverifiedEmail": null,
        "newPassword": null,
        "currentPassword": null,
        "verificationCodeIssuedDate": null,
        "verificationCode": null,
        "lastLoginAttemptIp": null,
        "authError": null,
        "inheritorOnDelete": null,
        "id": 471,
        "tempId": null,
        "draftId": null,
        "revisionId": null,
        "uid": "7df2c66c-1880-4621-a641-a9a14fb8bca3",
        "siteSettingsId": 471,
        "fieldLayoutId": null,
        "contentId": 304,
        "enabled": true,
        "archived": false,
        "siteId": 1,
        "title": null,
        "slug": null,
        "uri": null,
        "dateCreated": "2018-08-27T05:13:16-07:00",
        "dateUpdated": "2018-09-10T16:27:37-07:00",
        "dateDeleted": null,
        "trashed": false,
        "propagateAll": false,
        "newSiteIds": [],
        "resaving": false,
        "duplicateOf": null,
        "previewing": false,
        "hardDelete": false,
        "ref": "chrisanderson",
        "status": "suspended",
        "structureId": null,
        "url": null,
        "cooldownEndTime": null,
        "friendlyName": "Chris",
        "fullName": "Chris Anderson",
        "isCurrent": false,
        "name": "Chris Anderson",
        "preferredLanguage": null,
        "remainingCooldownTime": null
    },
    {
        "username": "danandmatt",
        "photoId": null,
        "firstName": "Daniel Abadi,",
        "lastName": "Matt Freels",
        "email": "matt+dan@fauna.com",
        "password": null,
        "admin": "0",
        "locked": "0",
        "suspended": "0",
        "pending": "0",
        "lastLoginDate": null,
        "invalidLoginCount": null,
        "lastInvalidLoginDate": null,
        "lockoutDate": null,
        "hasDashboard": "0",
        "passwordResetRequired": false,
        "lastPasswordChangeDate": null,
        "unverifiedEmail": null,
        "newPassword": null,
        "currentPassword": null,
        "verificationCodeIssuedDate": null,
        "verificationCode": null,
        "lastLoginAttemptIp": null,
        "authError": null,
        "inheritorOnDelete": null,
        "id": 1787,
        "tempId": null,
        "draftId": null,
        "revisionId": null,
        "uid": "261514d3-17b0-4f38-9713-67c311630685",
        "siteSettingsId": 1787,
        "fieldLayoutId": null,
        "contentId": 1351,
        "enabled": true,
        "archived": false,
        "siteId": 1,
        "title": null,
        "slug": null,
        "uri": null,
        "dateCreated": "2019-05-03T10:20:13-07:00",
        "dateUpdated": "2020-04-08T10:15:27-07:00",
        "dateDeleted": null,
        "trashed": false,
        "propagateAll": false,
        "newSiteIds": [],
        "resaving": false,
        "duplicateOf": null,
        "previewing": false,
        "hardDelete": false,
        "ref": "danandmatt",
        "status": "active",
        "structureId": null,
        "url": null,
        "cooldownEndTime": null,
        "friendlyName": "Daniel Abadi,",
        "fullName": "Daniel Abadi, Matt Freels",
        "isCurrent": false,
        "name": "Daniel Abadi, Matt Freels",
        "preferredLanguage": null,
        "remainingCooldownTime": null
    },
    {
        "username": "danielabadi",
        "photoId": null,
        "firstName": "Daniel J.",
        "lastName": "Abadi",
        "email": "dna@cs.yale.edu",
        "password": null,
        "admin": "0",
        "locked": "0",
        "suspended": "0",
        "pending": "0",
        "lastLoginDate": null,
        "invalidLoginCount": null,
        "lastInvalidLoginDate": null,
        "lockoutDate": null,
        "hasDashboard": "0",
        "passwordResetRequired": false,
        "lastPasswordChangeDate": null,
        "unverifiedEmail": null,
        "newPassword": null,
        "currentPassword": null,
        "verificationCodeIssuedDate": null,
        "verificationCode": null,
        "lastLoginAttemptIp": null,
        "authError": null,
        "inheritorOnDelete": null,
        "id": 472,
        "tempId": null,
        "draftId": null,
        "revisionId": null,
        "uid": "e99491c2-a7c1-4834-84da-716a211f586d",
        "siteSettingsId": 472,
        "fieldLayoutId": null,
        "contentId": 305,
        "enabled": true,
        "archived": false,
        "siteId": 1,
        "title": null,
        "slug": null,
        "uri": null,
        "dateCreated": "2018-08-27T05:13:44-07:00",
        "dateUpdated": "2018-12-12T17:50:38-08:00",
        "dateDeleted": null,
        "trashed": false,
        "propagateAll": false,
        "newSiteIds": [],
        "resaving": false,
        "duplicateOf": null,
        "previewing": false,
        "hardDelete": false,
        "ref": "danielabadi",
        "status": "active",
        "structureId": null,
        "url": null,
        "cooldownEndTime": null,
        "friendlyName": "Daniel J.",
        "fullName": "Daniel J. Abadi",
        "isCurrent": false,
        "name": "Daniel J. Abadi",
        "preferredLanguage": null,
        "remainingCooldownTime": null
    },
    {
        "username": "DanMeyers",
        "photoId": null,
        "firstName": "Dan",
        "lastName": "Meyers",
        "email": "dan.meyers@fauna.com",
        "password": null,
        "admin": "0",
        "locked": "0",
        "suspended": "0",
        "pending": "0",
        "lastLoginDate": null,
        "invalidLoginCount": null,
        "lastInvalidLoginDate": null,
        "lockoutDate": null,
        "hasDashboard": "0",
        "passwordResetRequired": false,
        "lastPasswordChangeDate": null,
        "unverifiedEmail": null,
        "newPassword": null,
        "currentPassword": null,
        "verificationCodeIssuedDate": null,
        "verificationCode": null,
        "lastLoginAttemptIp": null,
        "authError": null,
        "inheritorOnDelete": null,
        "id": 7019,
        "tempId": null,
        "draftId": null,
        "revisionId": null,
        "uid": "199752bc-9df2-4433-81d2-8ceea62696d5",
        "siteSettingsId": 7019,
        "fieldLayoutId": null,
        "contentId": 2440,
        "enabled": true,
        "archived": false,
        "siteId": 1,
        "title": null,
        "slug": null,
        "uri": null,
        "dateCreated": "2020-03-25T08:59:17-07:00",
        "dateUpdated": "2020-03-25T08:59:17-07:00",
        "dateDeleted": null,
        "trashed": false,
        "propagateAll": false,
        "newSiteIds": [],
        "resaving": false,
        "duplicateOf": null,
        "previewing": false,
        "hardDelete": false,
        "ref": "DanMeyers",
        "status": "active",
        "structureId": null,
        "url": null,
        "cooldownEndTime": null,
        "friendlyName": "Dan",
        "fullName": "Dan Meyers",
        "isCurrent": false,
        "name": "Dan Meyers",
        "preferredLanguage": null,
        "remainingCooldownTime": null
    },
    {
        "username": "DavidBarrat",
        "photoId": null,
        "firstName": "David",
        "lastName": "Barrat",
        "email": "david_barrat@fauna.com",
        "password": null,
        "admin": "0",
        "locked": "0",
        "suspended": "0",
        "pending": "0",
        "lastLoginDate": null,
        "invalidLoginCount": null,
        "lastInvalidLoginDate": null,
        "lockoutDate": null,
        "hasDashboard": "0",
        "passwordResetRequired": false,
        "lastPasswordChangeDate": null,
        "unverifiedEmail": null,
        "newPassword": null,
        "currentPassword": null,
        "verificationCodeIssuedDate": null,
        "verificationCode": null,
        "lastLoginAttemptIp": null,
        "authError": null,
        "inheritorOnDelete": null,
        "id": 6436,
        "tempId": null,
        "draftId": null,
        "revisionId": null,
        "uid": "1b7cbcfb-1068-4cf1-9d16-40ecaf77ac22",
        "siteSettingsId": 6436,
        "fieldLayoutId": null,
        "contentId": 2215,
        "enabled": true,
        "archived": false,
        "siteId": 1,
        "title": null,
        "slug": null,
        "uri": null,
        "dateCreated": "2019-11-18T15:46:29-08:00",
        "dateUpdated": "2019-11-18T15:46:47-08:00",
        "dateDeleted": null,
        "trashed": false,
        "propagateAll": false,
        "newSiteIds": [],
        "resaving": false,
        "duplicateOf": null,
        "previewing": false,
        "hardDelete": false,
        "ref": "DavidBarrat",
        "status": "active",
        "structureId": null,
        "url": null,
        "cooldownEndTime": null,
        "friendlyName": "David",
        "fullName": "David Barrat",
        "isCurrent": false,
        "name": "David Barrat",
        "preferredLanguage": null,
        "remainingCooldownTime": null
    },
    {
        "username": "Deba.Chatterjee",
        "photoId": "1392",
        "firstName": "Deba",
        "lastName": "Chatterjee",
        "email": "deba.chatterjee@fauna.com",
        "password": null,
        "admin": "1",
        "locked": "0",
        "suspended": "1",
        "pending": "0",
        "lastLoginDate": "2019-06-18T12:02:02-07:00",
        "invalidLoginCount": null,
        "lastInvalidLoginDate": null,
        "lockoutDate": null,
        "hasDashboard": "1",
        "passwordResetRequired": false,
        "lastPasswordChangeDate": null,
        "unverifiedEmail": null,
        "newPassword": null,
        "currentPassword": null,
        "verificationCodeIssuedDate": null,
        "verificationCode": null,
        "lastLoginAttemptIp": null,
        "authError": null,
        "inheritorOnDelete": null,
        "id": 1370,
        "tempId": null,
        "draftId": null,
        "revisionId": null,
        "uid": "975a45c8-ad39-4a9b-9aaa-3641f581da6b",
        "siteSettingsId": 1370,
        "fieldLayoutId": null,
        "contentId": 1034,
        "enabled": true,
        "archived": false,
        "siteId": 1,
        "title": null,
        "slug": null,
        "uri": null,
        "dateCreated": "2018-09-20T09:53:47-07:00",
        "dateUpdated": "2018-12-06T13:37:49-08:00",
        "dateDeleted": null,
        "trashed": false,
        "propagateAll": false,
        "newSiteIds": [],
        "resaving": false,
        "duplicateOf": null,
        "previewing": false,
        "hardDelete": false,
        "ref": "Deba.Chatterjee",
        "status": "suspended",
        "structureId": null,
        "url": null,
        "cooldownEndTime": null,
        "friendlyName": "Deba",
        "fullName": "Deba Chatterjee",
        "isCurrent": false,
        "name": "Deba Chatterjee",
        "preferredLanguage": null,
        "remainingCooldownTime": null
    },
    {
        "username": "Dennis.Duckworth",
        "photoId": "1453",
        "firstName": "Dennis",
        "lastName": "Duckworth",
        "email": "dennis.duckworth@fauna.com",
        "password": null,
        "admin": "1",
        "locked": "0",
        "suspended": "1",
        "pending": "0",
        "lastLoginDate": "2019-01-31T13:59:27-08:00",
        "invalidLoginCount": null,
        "lastInvalidLoginDate": null,
        "lockoutDate": null,
        "hasDashboard": "1",
        "passwordResetRequired": false,
        "lastPasswordChangeDate": null,
        "unverifiedEmail": null,
        "newPassword": null,
        "currentPassword": null,
        "verificationCodeIssuedDate": null,
        "verificationCode": null,
        "lastLoginAttemptIp": null,
        "authError": null,
        "inheritorOnDelete": null,
        "id": 473,
        "tempId": null,
        "draftId": null,
        "revisionId": null,
        "uid": "9a40d7b5-e5ab-4144-994c-9e7c628f5d91",
        "siteSettingsId": 473,
        "fieldLayoutId": null,
        "contentId": 306,
        "enabled": true,
        "archived": false,
        "siteId": 1,
        "title": null,
        "slug": null,
        "uri": null,
        "dateCreated": "2018-08-27T05:14:09-07:00",
        "dateUpdated": "2018-10-29T18:53:09-07:00",
        "dateDeleted": null,
        "trashed": false,
        "propagateAll": false,
        "newSiteIds": [],
        "resaving": false,
        "duplicateOf": null,
        "previewing": false,
        "hardDelete": false,
        "ref": "Dennis.Duckworth",
        "status": "suspended",
        "structureId": null,
        "url": null,
        "cooldownEndTime": null,
        "friendlyName": "Dennis",
        "fullName": "Dennis Duckworth",
        "isCurrent": false,
        "name": "Dennis Duckworth",
        "preferredLanguage": "en-US",
        "remainingCooldownTime": null
    },
    {
        "username": "dhruvgupta",
        "photoId": "1390",
        "firstName": "Dhruv",
        "lastName": "Gupta",
        "email": "dhruv@fauna.com",
        "password": null,
        "admin": "1",
        "locked": "0",
        "suspended": "0",
        "pending": "0",
        "lastLoginDate": "2020-10-14T21:18:42-07:00",
        "invalidLoginCount": null,
        "lastInvalidLoginDate": null,
        "lockoutDate": null,
        "hasDashboard": "1",
        "passwordResetRequired": false,
        "lastPasswordChangeDate": null,
        "unverifiedEmail": null,
        "newPassword": null,
        "currentPassword": null,
        "verificationCodeIssuedDate": null,
        "verificationCode": null,
        "lastLoginAttemptIp": null,
        "authError": null,
        "inheritorOnDelete": null,
        "id": 601,
        "tempId": null,
        "draftId": null,
        "revisionId": null,
        "uid": "6e0a2b54-6752-4995-a3b8-e8f0120e2949",
        "siteSettingsId": 601,
        "fieldLayoutId": null,
        "contentId": 395,
        "enabled": true,
        "archived": false,
        "siteId": 1,
        "title": null,
        "slug": null,
        "uri": null,
        "dateCreated": "2018-09-10T14:09:42-07:00",
        "dateUpdated": "2020-03-24T13:38:22-07:00",
        "dateDeleted": null,
        "trashed": false,
        "propagateAll": false,
        "newSiteIds": [],
        "resaving": false,
        "duplicateOf": null,
        "previewing": false,
        "hardDelete": false,
        "ref": "dhruvgupta",
        "status": "active",
        "structureId": null,
        "url": null,
        "cooldownEndTime": null,
        "friendlyName": "Dhruv",
        "fullName": "Dhruv Gupta",
        "isCurrent": false,
        "name": "Dhruv Gupta",
        "preferredLanguage": "en-US",
        "remainingCooldownTime": null
    },
    {
        "username": "ericberg",
        "photoId": null,
        "firstName": "Eric",
        "lastName": "Berg",
        "email": "eric.berg@fauna.com",
        "password": null,
        "admin": "1",
        "locked": "0",
        "suspended": "0",
        "pending": "0",
        "lastLoginDate": null,
        "invalidLoginCount": null,
        "lastInvalidLoginDate": null,
        "lockoutDate": null,
        "hasDashboard": "0",
        "passwordResetRequired": false,
        "lastPasswordChangeDate": null,
        "unverifiedEmail": null,
        "newPassword": null,
        "currentPassword": null,
        "verificationCodeIssuedDate": null,
        "verificationCode": null,
        "lastLoginAttemptIp": null,
        "authError": null,
        "inheritorOnDelete": null,
        "id": 8835,
        "tempId": null,
        "draftId": null,
        "revisionId": null,
        "uid": "f6e11bfb-6a26-4278-b4e3-870f1491d88d",
        "siteSettingsId": 8835,
        "fieldLayoutId": null,
        "contentId": 3020,
        "enabled": true,
        "archived": false,
        "siteId": 1,
        "title": null,
        "slug": null,
        "uri": null,
        "dateCreated": "2020-09-22T10:01:18-07:00",
        "dateUpdated": "2020-09-22T10:04:20-07:00",
        "dateDeleted": null,
        "trashed": false,
        "propagateAll": false,
        "newSiteIds": [],
        "resaving": false,
        "duplicateOf": null,
        "previewing": false,
        "hardDelete": false,
        "ref": "ericberg",
        "status": "active",
        "structureId": null,
        "url": null,
        "cooldownEndTime": null,
        "friendlyName": "Eric",
        "fullName": "Eric Berg",
        "isCurrent": false,
        "name": "Eric Berg",
        "preferredLanguage": null,
        "remainingCooldownTime": null
    },
    {
        "username": "evanw+mattF",
        "photoId": null,
        "firstName": "Evan Weaver &",
        "lastName": "Matt Freels",
        "email": "evanandmatt@fauna.com",
        "password": null,
        "admin": "0",
        "locked": "0",
        "suspended": "0",
        "pending": "0",
        "lastLoginDate": null,
        "invalidLoginCount": null,
        "lastInvalidLoginDate": null,
        "lockoutDate": null,
        "hasDashboard": "0",
        "passwordResetRequired": false,
        "lastPasswordChangeDate": null,
        "unverifiedEmail": null,
        "newPassword": null,
        "currentPassword": null,
        "verificationCodeIssuedDate": null,
        "verificationCode": null,
        "lastLoginAttemptIp": null,
        "authError": null,
        "inheritorOnDelete": null,
        "id": 8142,
        "tempId": null,
        "draftId": null,
        "revisionId": null,
        "uid": "4f813120-6c96-4c45-a5a6-e24277b104b4",
        "siteSettingsId": 8142,
        "fieldLayoutId": null,
        "contentId": 2740,
        "enabled": true,
        "archived": false,
        "siteId": 1,
        "title": null,
        "slug": null,
        "uri": null,
        "dateCreated": "2020-06-30T15:25:49-07:00",
        "dateUpdated": "2020-06-30T15:25:49-07:00",
        "dateDeleted": null,
        "trashed": false,
        "propagateAll": false,
        "newSiteIds": [],
        "resaving": false,
        "duplicateOf": null,
        "previewing": false,
        "hardDelete": false,
        "ref": "evanw+mattF",
        "status": "active",
        "structureId": null,
        "url": null,
        "cooldownEndTime": null,
        "friendlyName": "Evan Weaver &",
        "fullName": "Evan Weaver & Matt Freels",
        "isCurrent": false,
        "name": "Evan Weaver & Matt Freels",
        "preferredLanguage": null,
        "remainingCooldownTime": null
    },
    {
        "username": "evanweaver",
        "photoId": "1388",
        "firstName": "Evan",
        "lastName": "Weaver",
        "email": "evan@fauna.com",
        "password": null,
        "admin": "1",
        "locked": "0",
        "suspended": "0",
        "pending": "0",
        "lastLoginDate": "2020-01-15T13:35:57-08:00",
        "invalidLoginCount": null,
        "lastInvalidLoginDate": null,
        "lockoutDate": null,
        "hasDashboard": "1",
        "passwordResetRequired": false,
        "lastPasswordChangeDate": null,
        "unverifiedEmail": null,
        "newPassword": null,
        "currentPassword": null,
        "verificationCodeIssuedDate": null,
        "verificationCode": null,
        "lastLoginAttemptIp": null,
        "authError": null,
        "inheritorOnDelete": null,
        "id": 474,
        "tempId": null,
        "draftId": null,
        "revisionId": null,
        "uid": "4ed8858a-5ba0-4728-bc46-609f69d10759",
        "siteSettingsId": 474,
        "fieldLayoutId": null,
        "contentId": 307,
        "enabled": true,
        "archived": false,
        "siteId": 1,
        "title": null,
        "slug": null,
        "uri": null,
        "dateCreated": "2018-08-27T05:14:37-07:00",
        "dateUpdated": "2018-09-27T08:37:44-07:00",
        "dateDeleted": null,
        "trashed": false,
        "propagateAll": false,
        "newSiteIds": [],
        "resaving": false,
        "duplicateOf": null,
        "previewing": false,
        "hardDelete": false,
        "ref": "evanweaver",
        "status": "active",
        "structureId": null,
        "url": null,
        "cooldownEndTime": null,
        "friendlyName": "Evan",
        "fullName": "Evan Weaver",
        "isCurrent": false,
        "name": "Evan Weaver",
        "preferredLanguage": null,
        "remainingCooldownTime": null
    },
    {
        "username": "ewan.edwards",
        "photoId": null,
        "firstName": "Ewan",
        "lastName": "Edwards",
        "email": "ewan.edwards@fauna.com",
        "password": null,
        "admin": "0",
        "locked": "0",
        "suspended": "0",
        "pending": "0",
        "lastLoginDate": "2020-04-10T09:40:16-07:00",
        "invalidLoginCount": null,
        "lastInvalidLoginDate": null,
        "lockoutDate": null,
        "hasDashboard": "1",
        "passwordResetRequired": false,
        "lastPasswordChangeDate": null,
        "unverifiedEmail": null,
        "newPassword": null,
        "currentPassword": null,
        "verificationCodeIssuedDate": null,
        "verificationCode": null,
        "lastLoginAttemptIp": null,
        "authError": null,
        "inheritorOnDelete": null,
        "id": 1740,
        "tempId": null,
        "draftId": null,
        "revisionId": null,
        "uid": "f1d80d74-a203-450f-8fbd-2cf792e44780",
        "siteSettingsId": 1740,
        "fieldLayoutId": null,
        "contentId": 1317,
        "enabled": true,
        "archived": false,
        "siteId": 1,
        "title": null,
        "slug": null,
        "uri": null,
        "dateCreated": "2019-04-10T14:05:12-07:00",
        "dateUpdated": "2020-04-10T09:40:01-07:00",
        "dateDeleted": null,
        "trashed": false,
        "propagateAll": false,
        "newSiteIds": [],
        "resaving": false,
        "duplicateOf": null,
        "previewing": false,
        "hardDelete": false,
        "ref": "ewan.edwards",
        "status": "active",
        "structureId": null,
        "url": null,
        "cooldownEndTime": null,
        "friendlyName": "Ewan",
        "fullName": "Ewan Edwards",
        "isCurrent": false,
        "name": "Ewan Edwards",
        "preferredLanguage": "en-US",
        "remainingCooldownTime": null
    },
    {
        "username": "Francoarza",
        "photoId": null,
        "firstName": "",
        "lastName": "",
        "email": "franco@basement.studio",
        "password": null,
        "admin": "0",
        "locked": "0",
        "suspended": "0",
        "pending": "0",
        "lastLoginDate": null,
        "invalidLoginCount": null,
        "lastInvalidLoginDate": null,
        "lockoutDate": null,
        "hasDashboard": "0",
        "passwordResetRequired": false,
        "lastPasswordChangeDate": null,
        "unverifiedEmail": null,
        "newPassword": null,
        "currentPassword": null,
        "verificationCodeIssuedDate": null,
        "verificationCode": null,
        "lastLoginAttemptIp": null,
        "authError": null,
        "inheritorOnDelete": null,
        "id": 8870,
        "tempId": null,
        "draftId": null,
        "revisionId": null,
        "uid": "792b69f1-1a54-4b73-ab43-4b4885281842",
        "siteSettingsId": 8870,
        "fieldLayoutId": null,
        "contentId": 3037,
        "enabled": true,
        "archived": false,
        "siteId": 1,
        "title": null,
        "slug": null,
        "uri": null,
        "dateCreated": "2020-10-05T11:05:14-07:00",
        "dateUpdated": "2020-10-05T11:05:14-07:00",
        "dateDeleted": null,
        "trashed": false,
        "propagateAll": false,
        "newSiteIds": [],
        "resaving": false,
        "duplicateOf": null,
        "previewing": false,
        "hardDelete": false,
        "ref": "Francoarza",
        "status": "active",
        "structureId": null,
        "url": null,
        "cooldownEndTime": null,
        "friendlyName": "Francoarza",
        "fullName": null,
        "isCurrent": false,
        "name": "Francoarza",
        "preferredLanguage": null,
        "remainingCooldownTime": null
    },
    {
        "username": "gershoni",
        "photoId": null,
        "firstName": "Gershoni",
        "lastName": "Admin",
        "email": "info@fauna.com",
        "password": null,
        "admin": "0",
        "locked": "0",
        "suspended": "1",
        "pending": "0",
        "lastLoginDate": "2018-09-17T12:05:51-07:00",
        "invalidLoginCount": null,
        "lastInvalidLoginDate": null,
        "lockoutDate": "2018-08-24T16:54:00-07:00",
        "hasDashboard": "1",
        "passwordResetRequired": false,
        "lastPasswordChangeDate": null,
        "unverifiedEmail": null,
        "newPassword": null,
        "currentPassword": null,
        "verificationCodeIssuedDate": null,
        "verificationCode": null,
        "lastLoginAttemptIp": null,
        "authError": null,
        "inheritorOnDelete": null,
        "id": 1,
        "tempId": null,
        "draftId": null,
        "revisionId": null,
        "uid": "812b4e74-bba6-478c-9ab4-a2a9ae7bb487",
        "siteSettingsId": 1,
        "fieldLayoutId": null,
        "contentId": 1,
        "enabled": true,
        "archived": false,
        "siteId": 1,
        "title": null,
        "slug": null,
        "uri": null,
        "dateCreated": "2018-08-16T19:19:42-07:00",
        "dateUpdated": "2018-12-11T16:16:53-08:00",
        "dateDeleted": null,
        "trashed": false,
        "propagateAll": false,
        "newSiteIds": [],
        "resaving": false,
        "duplicateOf": null,
        "previewing": false,
        "hardDelete": false,
        "ref": "gershoni",
        "status": "suspended",
        "structureId": null,
        "url": null,
        "cooldownEndTime": null,
        "friendlyName": "Gershoni",
        "fullName": "Gershoni Admin",
        "isCurrent": false,
        "name": "Gershoni Admin",
        "preferredLanguage": "en-US",
        "remainingCooldownTime": null
    },
    {
        "username": "james.yang",
        "photoId": null,
        "firstName": "James",
        "lastName": "Yang",
        "email": "james.yang@fauna.com",
        "password": null,
        "admin": "0",
        "locked": "0",
        "suspended": "0",
        "pending": "0",
        "lastLoginDate": "2019-11-08T17:29:23-08:00",
        "invalidLoginCount": null,
        "lastInvalidLoginDate": null,
        "lockoutDate": null,
        "hasDashboard": "1",
        "passwordResetRequired": false,
        "lastPasswordChangeDate": null,
        "unverifiedEmail": null,
        "newPassword": null,
        "currentPassword": null,
        "verificationCodeIssuedDate": null,
        "verificationCode": null,
        "lastLoginAttemptIp": null,
        "authError": null,
        "inheritorOnDelete": null,
        "id": 1788,
        "tempId": null,
        "draftId": null,
        "revisionId": null,
        "uid": "04b5c952-d1a4-412b-9c54-d84ec8e36bc5",
        "siteSettingsId": 1788,
        "fieldLayoutId": null,
        "contentId": 1352,
        "enabled": true,
        "archived": false,
        "siteId": 1,
        "title": null,
        "slug": null,
        "uri": null,
        "dateCreated": "2019-05-03T15:51:32-07:00",
        "dateUpdated": "2019-05-03T15:59:58-07:00",
        "dateDeleted": null,
        "trashed": false,
        "propagateAll": false,
        "newSiteIds": [],
        "resaving": false,
        "duplicateOf": null,
        "previewing": false,
        "hardDelete": false,
        "ref": "james.yang",
        "status": "active",
        "structureId": null,
        "url": null,
        "cooldownEndTime": null,
        "friendlyName": "James",
        "fullName": "James Yang",
        "isCurrent": false,
        "name": "James Yang",
        "preferredLanguage": null,
        "remainingCooldownTime": null
    },
    {
        "username": "jessicanewell",
        "photoId": null,
        "firstName": "Jessie",
        "lastName": "Newell",
        "email": "jessica.newell@fauna.com",
        "password": null,
        "admin": "1",
        "locked": "0",
        "suspended": "0",
        "pending": "0",
        "lastLoginDate": "2020-10-01T10:05:43-07:00",
        "invalidLoginCount": null,
        "lastInvalidLoginDate": null,
        "lockoutDate": null,
        "hasDashboard": "1",
        "passwordResetRequired": false,
        "lastPasswordChangeDate": null,
        "unverifiedEmail": null,
        "newPassword": null,
        "currentPassword": null,
        "verificationCodeIssuedDate": null,
        "verificationCode": null,
        "lastLoginAttemptIp": null,
        "authError": null,
        "inheritorOnDelete": null,
        "id": 603,
        "tempId": null,
        "draftId": null,
        "revisionId": null,
        "uid": "a960d08c-83ab-4c18-8c19-c7798513d847",
        "siteSettingsId": 603,
        "fieldLayoutId": null,
        "contentId": 397,
        "enabled": true,
        "archived": false,
        "siteId": 1,
        "title": null,
        "slug": null,
        "uri": null,
        "dateCreated": "2018-09-10T14:21:01-07:00",
        "dateUpdated": "2018-09-10T15:33:22-07:00",
        "dateDeleted": null,
        "trashed": false,
        "propagateAll": false,
        "newSiteIds": [],
        "resaving": false,
        "duplicateOf": null,
        "previewing": false,
        "hardDelete": false,
        "ref": "jessicanewell",
        "status": "active",
        "structureId": null,
        "url": null,
        "cooldownEndTime": null,
        "friendlyName": "Jessie",
        "fullName": "Jessie Newell",
        "isCurrent": false,
        "name": "Jessie Newell",
        "preferredLanguage": "en-US",
        "remainingCooldownTime": null
    },
    {
        "username": "jmiller",
        "photoId": null,
        "firstName": "John",
        "lastName": "Miller, III",
        "email": "jmiller@fauna.com",
        "password": null,
        "admin": "0",
        "locked": "0",
        "suspended": "0",
        "pending": "0",
        "lastLoginDate": null,
        "invalidLoginCount": null,
        "lastInvalidLoginDate": null,
        "lockoutDate": null,
        "hasDashboard": "0",
        "passwordResetRequired": false,
        "lastPasswordChangeDate": null,
        "unverifiedEmail": null,
        "newPassword": null,
        "currentPassword": null,
        "verificationCodeIssuedDate": null,
        "verificationCode": null,
        "lastLoginAttemptIp": null,
        "authError": null,
        "inheritorOnDelete": null,
        "id": 475,
        "tempId": null,
        "draftId": null,
        "revisionId": null,
        "uid": "0c807d8a-cd99-47fd-94b4-7553b0837ff8",
        "siteSettingsId": 475,
        "fieldLayoutId": null,
        "contentId": 308,
        "enabled": true,
        "archived": false,
        "siteId": 1,
        "title": null,
        "slug": null,
        "uri": null,
        "dateCreated": "2018-08-27T05:15:04-07:00",
        "dateUpdated": "2019-09-11T10:31:16-07:00",
        "dateDeleted": null,
        "trashed": false,
        "propagateAll": false,
        "newSiteIds": [],
        "resaving": false,
        "duplicateOf": null,
        "previewing": false,
        "hardDelete": false,
        "ref": "jmiller",
        "status": "active",
        "structureId": null,
        "url": null,
        "cooldownEndTime": null,
        "friendlyName": "John",
        "fullName": "John Miller, III",
        "isCurrent": false,
        "name": "John Miller, III",
        "preferredLanguage": null,
        "remainingCooldownTime": null
    },
    {
        "username": "JohnMandSummer",
        "photoId": null,
        "firstName": "John Miller III and",
        "lastName": "Summer Schrader",
        "email": "john+summer@fauna.com",
        "password": null,
        "admin": "0",
        "locked": "0",
        "suspended": "0",
        "pending": "0",
        "lastLoginDate": null,
        "invalidLoginCount": null,
        "lastInvalidLoginDate": null,
        "lockoutDate": null,
        "hasDashboard": "0",
        "passwordResetRequired": false,
        "lastPasswordChangeDate": null,
        "unverifiedEmail": null,
        "newPassword": null,
        "currentPassword": null,
        "verificationCodeIssuedDate": null,
        "verificationCode": null,
        "lastLoginAttemptIp": null,
        "authError": null,
        "inheritorOnDelete": null,
        "id": 7038,
        "tempId": null,
        "draftId": null,
        "revisionId": null,
        "uid": "5f2c2c21-55bb-4b38-bf87-9c4db2021997",
        "siteSettingsId": 7038,
        "fieldLayoutId": null,
        "contentId": 2448,
        "enabled": true,
        "archived": false,
        "siteId": 1,
        "title": null,
        "slug": null,
        "uri": null,
        "dateCreated": "2020-04-08T10:16:00-07:00",
        "dateUpdated": "2020-04-08T10:16:00-07:00",
        "dateDeleted": null,
        "trashed": false,
        "propagateAll": false,
        "newSiteIds": [],
        "resaving": false,
        "duplicateOf": null,
        "previewing": false,
        "hardDelete": false,
        "ref": "JohnMandSummer",
        "status": "active",
        "structureId": null,
        "url": null,
        "cooldownEndTime": null,
        "friendlyName": "John Miller III and",
        "fullName": "John Miller III and Summer Schrader",
        "isCurrent": false,
        "name": "John Miller III and Summer Schrader",
        "preferredLanguage": null,
        "remainingCooldownTime": null
    },
    {
        "username": "Julianbenegas",
        "photoId": null,
        "firstName": "",
        "lastName": "",
        "email": "julian@basement.studio",
        "password": null,
        "admin": "1",
        "locked": "0",
        "suspended": "0",
        "pending": "0",
        "lastLoginDate": "2020-10-21T05:42:27-07:00",
        "invalidLoginCount": null,
        "lastInvalidLoginDate": null,
        "lockoutDate": null,
        "hasDashboard": "1",
        "passwordResetRequired": false,
        "lastPasswordChangeDate": null,
        "unverifiedEmail": null,
        "newPassword": null,
        "currentPassword": null,
        "verificationCodeIssuedDate": null,
        "verificationCode": null,
        "lastLoginAttemptIp": null,
        "authError": null,
        "inheritorOnDelete": null,
        "id": 8871,
        "tempId": null,
        "draftId": null,
        "revisionId": null,
        "uid": "aa3be4d9-582d-4e42-a9e1-c6bc35cc1749",
        "siteSettingsId": 8871,
        "fieldLayoutId": null,
        "contentId": 3038,
        "enabled": true,
        "archived": false,
        "siteId": 1,
        "title": null,
        "slug": null,
        "uri": null,
        "dateCreated": "2020-10-05T11:06:01-07:00",
        "dateUpdated": "2020-10-06T10:28:23-07:00",
        "dateDeleted": null,
        "trashed": false,
        "propagateAll": false,
        "newSiteIds": [],
        "resaving": false,
        "duplicateOf": null,
        "previewing": false,
        "hardDelete": false,
        "ref": "Julianbenegas",
        "status": "active",
        "structureId": null,
        "url": null,
        "cooldownEndTime": null,
        "friendlyName": "Julianbenegas",
        "fullName": null,
        "isCurrent": false,
        "name": "Julianbenegas",
        "preferredLanguage": null,
        "remainingCooldownTime": null
    },
    {
        "username": "laurenrother",
        "photoId": null,
        "firstName": "Lauren",
        "lastName": "Rother",
        "email": "lauren@fauna.com",
        "password": null,
        "admin": "0",
        "locked": "0",
        "suspended": "1",
        "pending": "1",
        "lastLoginDate": null,
        "invalidLoginCount": null,
        "lastInvalidLoginDate": null,
        "lockoutDate": null,
        "hasDashboard": "0",
        "passwordResetRequired": false,
        "lastPasswordChangeDate": null,
        "unverifiedEmail": null,
        "newPassword": null,
        "currentPassword": null,
        "verificationCodeIssuedDate": null,
        "verificationCode": null,
        "lastLoginAttemptIp": null,
        "authError": null,
        "inheritorOnDelete": null,
        "id": 476,
        "tempId": null,
        "draftId": null,
        "revisionId": null,
        "uid": "8ab2aa74-6735-484b-b3f9-be8ce6521fdc",
        "siteSettingsId": 476,
        "fieldLayoutId": null,
        "contentId": 309,
        "enabled": true,
        "archived": false,
        "siteId": 1,
        "title": null,
        "slug": null,
        "uri": null,
        "dateCreated": "2018-08-27T05:15:23-07:00",
        "dateUpdated": "2018-08-27T05:15:23-07:00",
        "dateDeleted": null,
        "trashed": false,
        "propagateAll": false,
        "newSiteIds": [],
        "resaving": false,
        "duplicateOf": null,
        "previewing": false,
        "hardDelete": false,
        "ref": "laurenrother",
        "status": "suspended",
        "structureId": null,
        "url": null,
        "cooldownEndTime": null,
        "friendlyName": "Lauren",
        "fullName": "Lauren Rother",
        "isCurrent": false,
        "name": "Lauren Rother",
        "preferredLanguage": null,
        "remainingCooldownTime": null
    },
    {
        "username": "Leo_Regnier",
        "photoId": null,
        "firstName": "Leo",
        "lastName": "Regnier",
        "email": "leonardo.regnier@fauna.com",
        "password": null,
        "admin": "0",
        "locked": "0",
        "suspended": "0",
        "pending": "0",
        "lastLoginDate": null,
        "invalidLoginCount": null,
        "lastInvalidLoginDate": null,
        "lockoutDate": null,
        "hasDashboard": "0",
        "passwordResetRequired": false,
        "lastPasswordChangeDate": null,
        "unverifiedEmail": null,
        "newPassword": null,
        "currentPassword": null,
        "verificationCodeIssuedDate": null,
        "verificationCode": null,
        "lastLoginAttemptIp": null,
        "authError": null,
        "inheritorOnDelete": null,
        "id": 3110,
        "tempId": null,
        "draftId": null,
        "revisionId": null,
        "uid": "3f6d1b5e-58f8-4f15-bbe1-6f276ffe9aa0",
        "siteSettingsId": 3110,
        "fieldLayoutId": null,
        "contentId": 1662,
        "enabled": true,
        "archived": false,
        "siteId": 1,
        "title": null,
        "slug": null,
        "uri": null,
        "dateCreated": "2019-07-31T15:06:02-07:00",
        "dateUpdated": "2019-07-31T16:40:24-07:00",
        "dateDeleted": null,
        "trashed": false,
        "propagateAll": false,
        "newSiteIds": [],
        "resaving": false,
        "duplicateOf": null,
        "previewing": false,
        "hardDelete": false,
        "ref": "Leo_Regnier",
        "status": "active",
        "structureId": null,
        "url": null,
        "cooldownEndTime": null,
        "friendlyName": "Leo",
        "fullName": "Leo Regnier",
        "isCurrent": false,
        "name": "Leo Regnier",
        "preferredLanguage": null,
        "remainingCooldownTime": null
    },
    {
        "username": "lewis",
        "photoId": "1845",
        "firstName": "Lewis",
        "lastName": "King",
        "email": "lewis.king@fauna.com",
        "password": null,
        "admin": "1",
        "locked": "0",
        "suspended": "0",
        "pending": "0",
        "lastLoginDate": "2020-04-24T13:11:44-07:00",
        "invalidLoginCount": null,
        "lastInvalidLoginDate": null,
        "lockoutDate": null,
        "hasDashboard": "1",
        "passwordResetRequired": false,
        "lastPasswordChangeDate": null,
        "unverifiedEmail": null,
        "newPassword": null,
        "currentPassword": null,
        "verificationCodeIssuedDate": null,
        "verificationCode": null,
        "lastLoginAttemptIp": null,
        "authError": null,
        "inheritorOnDelete": null,
        "id": 1820,
        "tempId": null,
        "draftId": null,
        "revisionId": null,
        "uid": "10717389-b024-4dbf-9fb6-01cb7580a889",
        "siteSettingsId": 1820,
        "fieldLayoutId": null,
        "contentId": 1384,
        "enabled": true,
        "archived": false,
        "siteId": 1,
        "title": null,
        "slug": null,
        "uri": null,
        "dateCreated": "2019-06-14T14:23:45-07:00",
        "dateUpdated": "2019-07-12T14:48:38-07:00",
        "dateDeleted": null,
        "trashed": false,
        "propagateAll": false,
        "newSiteIds": [],
        "resaving": false,
        "duplicateOf": null,
        "previewing": false,
        "hardDelete": false,
        "ref": "lewis",
        "status": "active",
        "structureId": null,
        "url": null,
        "cooldownEndTime": null,
        "friendlyName": "Lewis",
        "fullName": "Lewis King",
        "isCurrent": false,
        "name": "Lewis King",
        "preferredLanguage": "en-US",
        "remainingCooldownTime": null
    },
    {
        "username": "Mahesh",
        "photoId": null,
        "firstName": "Mahesh",
        "lastName": "Iyer",
        "email": "mahesh.iyer@fauna.com",
        "password": null,
        "admin": "1",
        "locked": "0",
        "suspended": "0",
        "pending": "0",
        "lastLoginDate": "2018-11-20T18:00:35-08:00",
        "invalidLoginCount": null,
        "lastInvalidLoginDate": null,
        "lockoutDate": null,
        "hasDashboard": "1",
        "passwordResetRequired": false,
        "lastPasswordChangeDate": null,
        "unverifiedEmail": null,
        "newPassword": null,
        "currentPassword": null,
        "verificationCodeIssuedDate": null,
        "verificationCode": null,
        "lastLoginAttemptIp": null,
        "authError": null,
        "inheritorOnDelete": null,
        "id": 1372,
        "tempId": null,
        "draftId": null,
        "revisionId": null,
        "uid": "e7357ffd-9e6e-4748-b0c7-3226f12f221d",
        "siteSettingsId": 1372,
        "fieldLayoutId": null,
        "contentId": 1036,
        "enabled": true,
        "archived": false,
        "siteId": 1,
        "title": null,
        "slug": null,
        "uri": null,
        "dateCreated": "2018-09-20T10:17:52-07:00",
        "dateUpdated": "2018-11-20T18:00:26-08:00",
        "dateDeleted": null,
        "trashed": false,
        "propagateAll": false,
        "newSiteIds": [],
        "resaving": false,
        "duplicateOf": null,
        "previewing": false,
        "hardDelete": false,
        "ref": "Mahesh",
        "status": "active",
        "structureId": null,
        "url": null,
        "cooldownEndTime": null,
        "friendlyName": "Mahesh",
        "fullName": "Mahesh Iyer",
        "isCurrent": false,
        "name": "Mahesh Iyer",
        "preferredLanguage": null,
        "remainingCooldownTime": null
    },
    {
        "username": "MattAttaway",
        "photoId": null,
        "firstName": "Matt",
        "lastName": "Attaway",
        "email": "matt.attaway@fauna.com",
        "password": null,
        "admin": "0",
        "locked": "0",
        "suspended": "0",
        "pending": "0",
        "lastLoginDate": null,
        "invalidLoginCount": null,
        "lastInvalidLoginDate": null,
        "lockoutDate": null,
        "hasDashboard": "0",
        "passwordResetRequired": false,
        "lastPasswordChangeDate": null,
        "unverifiedEmail": null,
        "newPassword": null,
        "currentPassword": null,
        "verificationCodeIssuedDate": null,
        "verificationCode": null,
        "lastLoginAttemptIp": null,
        "authError": null,
        "inheritorOnDelete": null,
        "id": 6421,
        "tempId": null,
        "draftId": null,
        "revisionId": null,
        "uid": "fd9f19b8-6e7e-4bd3-908d-2e10797baa62",
        "siteSettingsId": 6421,
        "fieldLayoutId": null,
        "contentId": 2200,
        "enabled": true,
        "archived": false,
        "siteId": 1,
        "title": null,
        "slug": null,
        "uri": null,
        "dateCreated": "2019-11-12T09:16:22-08:00",
        "dateUpdated": "2019-11-12T09:16:22-08:00",
        "dateDeleted": null,
        "trashed": false,
        "propagateAll": false,
        "newSiteIds": [],
        "resaving": false,
        "duplicateOf": null,
        "previewing": false,
        "hardDelete": false,
        "ref": "MattAttaway",
        "status": "active",
        "structureId": null,
        "url": null,
        "cooldownEndTime": null,
        "friendlyName": "Matt",
        "fullName": "Matt Attaway",
        "isCurrent": false,
        "name": "Matt Attaway",
        "preferredLanguage": null,
        "remainingCooldownTime": null
    },
    {
        "username": "mattfandLewis",
        "photoId": null,
        "firstName": "Matt Freels,",
        "lastName": "Lewis King",
        "email": "matt+lewis@fauna.com",
        "password": null,
        "admin": "0",
        "locked": "0",
        "suspended": "0",
        "pending": "0",
        "lastLoginDate": null,
        "invalidLoginCount": null,
        "lastInvalidLoginDate": null,
        "lockoutDate": null,
        "hasDashboard": "0",
        "passwordResetRequired": false,
        "lastPasswordChangeDate": null,
        "unverifiedEmail": null,
        "newPassword": null,
        "currentPassword": null,
        "verificationCodeIssuedDate": null,
        "verificationCode": null,
        "lastLoginAttemptIp": null,
        "authError": null,
        "inheritorOnDelete": null,
        "id": 6158,
        "tempId": null,
        "draftId": null,
        "revisionId": null,
        "uid": "62b4354b-47e6-46b6-9b8d-fbbb596e98e1",
        "siteSettingsId": 6158,
        "fieldLayoutId": null,
        "contentId": 2120,
        "enabled": true,
        "archived": false,
        "siteId": 1,
        "title": null,
        "slug": null,
        "uri": null,
        "dateCreated": "2019-10-01T10:12:14-07:00",
        "dateUpdated": "2019-10-01T10:12:14-07:00",
        "dateDeleted": null,
        "trashed": false,
        "propagateAll": false,
        "newSiteIds": [],
        "resaving": false,
        "duplicateOf": null,
        "previewing": false,
        "hardDelete": false,
        "ref": "mattfandLewis",
        "status": "active",
        "structureId": null,
        "url": null,
        "cooldownEndTime": null,
        "friendlyName": "Matt Freels,",
        "fullName": "Matt Freels, Lewis King",
        "isCurrent": false,
        "name": "Matt Freels, Lewis King",
        "preferredLanguage": null,
        "remainingCooldownTime": null
    },
    {
        "username": "mattfreels",
        "photoId": "1480",
        "firstName": "Matt",
        "lastName": "Freels",
        "email": "matt@fauna.com",
        "password": null,
        "admin": "1",
        "locked": "0",
        "suspended": "0",
        "pending": "0",
        "lastLoginDate": "2019-06-28T16:20:16-07:00",
        "invalidLoginCount": null,
        "lastInvalidLoginDate": null,
        "lockoutDate": null,
        "hasDashboard": "1",
        "passwordResetRequired": false,
        "lastPasswordChangeDate": null,
        "unverifiedEmail": null,
        "newPassword": null,
        "currentPassword": null,
        "verificationCodeIssuedDate": null,
        "verificationCode": null,
        "lastLoginAttemptIp": null,
        "authError": null,
        "inheritorOnDelete": null,
        "id": 477,
        "tempId": null,
        "draftId": null,
        "revisionId": null,
        "uid": "15a2e31d-50cd-4a66-b84e-56132ced38d4",
        "siteSettingsId": 477,
        "fieldLayoutId": null,
        "contentId": 310,
        "enabled": true,
        "archived": false,
        "siteId": 1,
        "title": null,
        "slug": null,
        "uri": null,
        "dateCreated": "2018-08-27T05:15:58-07:00",
        "dateUpdated": "2018-11-15T04:47:09-08:00",
        "dateDeleted": null,
        "trashed": false,
        "propagateAll": false,
        "newSiteIds": [],
        "resaving": false,
        "duplicateOf": null,
        "previewing": false,
        "hardDelete": false,
        "ref": "mattfreels",
        "status": "active",
        "structureId": null,
        "url": null,
        "cooldownEndTime": null,
        "friendlyName": "Matt",
        "fullName": "Matt Freels",
        "isCurrent": false,
        "name": "Matt Freels",
        "preferredLanguage": null,
        "remainingCooldownTime": null
    },
    {
        "username": "nathan_taylor",
        "photoId": null,
        "firstName": "Nathan",
        "lastName": "Taylor",
        "email": "nathan@fauna.com",
        "password": null,
        "admin": "0",
        "locked": "0",
        "suspended": "1",
        "pending": "1",
        "lastLoginDate": null,
        "invalidLoginCount": null,
        "lastInvalidLoginDate": null,
        "lockoutDate": null,
        "hasDashboard": "0",
        "passwordResetRequired": false,
        "lastPasswordChangeDate": null,
        "unverifiedEmail": null,
        "newPassword": null,
        "currentPassword": null,
        "verificationCodeIssuedDate": null,
        "verificationCode": null,
        "lastLoginAttemptIp": null,
        "authError": null,
        "inheritorOnDelete": null,
        "id": 478,
        "tempId": null,
        "draftId": null,
        "revisionId": null,
        "uid": "1c604cb7-afa5-4ad2-9ed4-80b1393ae598",
        "siteSettingsId": 478,
        "fieldLayoutId": null,
        "contentId": 311,
        "enabled": true,
        "archived": false,
        "siteId": 1,
        "title": null,
        "slug": null,
        "uri": null,
        "dateCreated": "2018-08-27T05:16:27-07:00",
        "dateUpdated": "2018-08-27T05:16:27-07:00",
        "dateDeleted": null,
        "trashed": false,
        "propagateAll": false,
        "newSiteIds": [],
        "resaving": false,
        "duplicateOf": null,
        "previewing": false,
        "hardDelete": false,
        "ref": "nathan_taylor",
        "status": "suspended",
        "structureId": null,
        "url": null,
        "cooldownEndTime": null,
        "friendlyName": "Nathan",
        "fullName": "Nathan Taylor",
        "isCurrent": false,
        "name": "Nathan Taylor",
        "preferredLanguage": null,
        "remainingCooldownTime": null
    },
    {
        "username": "PierBover",
        "photoId": null,
        "firstName": "Pier",
        "lastName": "Bover",
        "email": "pier.bover@fauna.com",
        "password": null,
        "admin": "0",
        "locked": "0",
        "suspended": "0",
        "pending": "0",
        "lastLoginDate": null,
        "invalidLoginCount": null,
        "lastInvalidLoginDate": null,
        "lockoutDate": null,
        "hasDashboard": "0",
        "passwordResetRequired": false,
        "lastPasswordChangeDate": null,
        "unverifiedEmail": null,
        "newPassword": null,
        "currentPassword": null,
        "verificationCodeIssuedDate": null,
        "verificationCode": null,
        "lastLoginAttemptIp": null,
        "authError": null,
        "inheritorOnDelete": null,
        "id": 7655,
        "tempId": null,
        "draftId": null,
        "revisionId": null,
        "uid": "8e1befb1-f4f6-4cf2-aa12-c6c1e4e1cdec",
        "siteSettingsId": 7655,
        "fieldLayoutId": null,
        "contentId": 2627,
        "enabled": true,
        "archived": false,
        "siteId": 1,
        "title": null,
        "slug": null,
        "uri": null,
        "dateCreated": "2020-06-22T12:23:55-07:00",
        "dateUpdated": "2020-06-22T12:25:01-07:00",
        "dateDeleted": null,
        "trashed": false,
        "propagateAll": false,
        "newSiteIds": [],
        "resaving": false,
        "duplicateOf": null,
        "previewing": false,
        "hardDelete": false,
        "ref": "PierBover",
        "status": "active",
        "structureId": null,
        "url": null,
        "cooldownEndTime": null,
        "friendlyName": "Pier",
        "fullName": "Pier Bover",
        "isCurrent": false,
        "name": "Pier Bover",
        "preferredLanguage": null,
        "remainingCooldownTime": null
    },
    {
        "username": "ryan.knight",
        "photoId": null,
        "firstName": "Ryan",
        "lastName": "Knight",
        "email": "ryan.knight@fauna.com",
        "password": null,
        "admin": "0",
        "locked": "0",
        "suspended": "1",
        "pending": "1",
        "lastLoginDate": null,
        "invalidLoginCount": null,
        "lastInvalidLoginDate": null,
        "lockoutDate": null,
        "hasDashboard": "0",
        "passwordResetRequired": false,
        "lastPasswordChangeDate": null,
        "unverifiedEmail": null,
        "newPassword": null,
        "currentPassword": null,
        "verificationCodeIssuedDate": null,
        "verificationCode": null,
        "lastLoginAttemptIp": null,
        "authError": null,
        "inheritorOnDelete": null,
        "id": 479,
        "tempId": null,
        "draftId": null,
        "revisionId": null,
        "uid": "995a79d3-e435-4e3b-904e-40c82ae39dea",
        "siteSettingsId": 479,
        "fieldLayoutId": null,
        "contentId": 312,
        "enabled": true,
        "archived": false,
        "siteId": 1,
        "title": null,
        "slug": null,
        "uri": null,
        "dateCreated": "2018-08-27T05:16:53-07:00",
        "dateUpdated": "2018-08-27T05:16:53-07:00",
        "dateDeleted": null,
        "trashed": false,
        "propagateAll": false,
        "newSiteIds": [],
        "resaving": false,
        "duplicateOf": null,
        "previewing": false,
        "hardDelete": false,
        "ref": "ryan.knight",
        "status": "suspended",
        "structureId": null,
        "url": null,
        "cooldownEndTime": null,
        "friendlyName": "Ryan",
        "fullName": "Ryan Knight",
        "isCurrent": false,
        "name": "Ryan Knight",
        "preferredLanguage": null,
        "remainingCooldownTime": null
    },
    {
        "username": "sheeba",
        "photoId": "1554",
        "firstName": "Sheeba",
        "lastName": "Abraham",
        "email": "sheeba.abraham@velotio.com",
        "password": null,
        "admin": "1",
        "locked": "0",
        "suspended": "0",
        "pending": "0",
        "lastLoginDate": "2020-10-21T06:14:30-07:00",
        "invalidLoginCount": null,
        "lastInvalidLoginDate": null,
        "lockoutDate": null,
        "hasDashboard": "1",
        "passwordResetRequired": false,
        "lastPasswordChangeDate": null,
        "unverifiedEmail": null,
        "newPassword": null,
        "currentPassword": null,
        "verificationCodeIssuedDate": null,
        "verificationCode": null,
        "lastLoginAttemptIp": null,
        "authError": null,
        "inheritorOnDelete": null,
        "id": 643,
        "tempId": null,
        "draftId": null,
        "revisionId": null,
        "uid": "49e1abd3-f752-43b8-b080-a8e66e2a9bda",
        "siteSettingsId": 643,
        "fieldLayoutId": null,
        "contentId": 434,
        "enabled": true,
        "archived": false,
        "siteId": 1,
        "title": null,
        "slug": null,
        "uri": null,
        "dateCreated": "2018-09-13T10:23:08-07:00",
        "dateUpdated": "2018-12-04T22:56:47-08:00",
        "dateDeleted": null,
        "trashed": false,
        "propagateAll": false,
        "newSiteIds": [],
        "resaving": false,
        "duplicateOf": null,
        "previewing": false,
        "hardDelete": false,
        "ref": "sheeba",
        "status": "active",
        "structureId": null,
        "url": null,
        "cooldownEndTime": null,
        "friendlyName": "Sheeba",
        "fullName": "Sheeba Abraham",
        "isCurrent": true,
        "name": "Sheeba Abraham",
        "preferredLanguage": "en-US",
        "remainingCooldownTime": null
    },
    {
        "username": "summerschrader",
        "photoId": null,
        "firstName": "Summer",
        "lastName": "Schrader",
        "email": "summer.schrader@fauna.com",
        "password": null,
        "admin": "1",
        "locked": "0",
        "suspended": "0",
        "pending": "0",
        "lastLoginDate": "2020-06-29T09:48:32-07:00",
        "invalidLoginCount": null,
        "lastInvalidLoginDate": null,
        "lockoutDate": null,
        "hasDashboard": "1",
        "passwordResetRequired": false,
        "lastPasswordChangeDate": null,
        "unverifiedEmail": null,
        "newPassword": null,
        "currentPassword": null,
        "verificationCodeIssuedDate": null,
        "verificationCode": null,
        "lastLoginAttemptIp": null,
        "authError": null,
        "inheritorOnDelete": null,
        "id": 602,
        "tempId": null,
        "draftId": null,
        "revisionId": null,
        "uid": "1cd8a932-c38b-46a6-955c-affde40c9d0e",
        "siteSettingsId": 602,
        "fieldLayoutId": null,
        "contentId": 396,
        "enabled": true,
        "archived": false,
        "siteId": 1,
        "title": null,
        "slug": null,
        "uri": null,
        "dateCreated": "2018-09-10T14:10:31-07:00",
        "dateUpdated": "2020-06-08T08:04:55-07:00",
        "dateDeleted": null,
        "trashed": false,
        "propagateAll": false,
        "newSiteIds": [],
        "resaving": false,
        "duplicateOf": null,
        "previewing": false,
        "hardDelete": false,
        "ref": "summerschrader",
        "status": "active",
        "structureId": null,
        "url": null,
        "cooldownEndTime": null,
        "friendlyName": "Summer",
        "fullName": "Summer Schrader",
        "isCurrent": false,
        "name": "Summer Schrader",
        "preferredLanguage": null,
        "remainingCooldownTime": null
    },
    {
        "username": "TigranTerian",
        "photoId": null,
        "firstName": "Tigran",
        "lastName": "Terian",
        "email": "tigranterian@fauna.com",
        "password": null,
        "admin": "0",
        "locked": "0",
        "suspended": "0",
        "pending": "0",
        "lastLoginDate": null,
        "invalidLoginCount": null,
        "lastInvalidLoginDate": null,
        "lockoutDate": null,
        "hasDashboard": "0",
        "passwordResetRequired": false,
        "lastPasswordChangeDate": null,
        "unverifiedEmail": null,
        "newPassword": null,
        "currentPassword": null,
        "verificationCodeIssuedDate": null,
        "verificationCode": null,
        "lastLoginAttemptIp": null,
        "authError": null,
        "inheritorOnDelete": null,
        "id": 6140,
        "tempId": null,
        "draftId": null,
        "revisionId": null,
        "uid": "f85023f3-1ed5-473f-9ff6-2715fb773f0b",
        "siteSettingsId": 6140,
        "fieldLayoutId": null,
        "contentId": 2102,
        "enabled": true,
        "archived": false,
        "siteId": 1,
        "title": null,
        "slug": null,
        "uri": null,
        "dateCreated": "2019-09-25T13:45:21-07:00",
        "dateUpdated": "2019-09-25T13:45:21-07:00",
        "dateDeleted": null,
        "trashed": false,
        "propagateAll": false,
        "newSiteIds": [],
        "resaving": false,
        "duplicateOf": null,
        "previewing": false,
        "hardDelete": false,
        "ref": "TigranTerian",
        "status": "active",
        "structureId": null,
        "url": null,
        "cooldownEndTime": null,
        "friendlyName": "Tigran",
        "fullName": "Tigran Terian",
        "isCurrent": false,
        "name": "Tigran Terian",
        "preferredLanguage": null,
        "remainingCooldownTime": null
    },
    {
        "username": "tyler",
        "photoId": null,
        "firstName": "Tyler",
        "lastName": "Hannan",
        "email": "tyler@fauna.com",
        "password": null,
        "admin": "0",
        "locked": "0",
        "suspended": "0",
        "pending": "0",
        "lastLoginDate": null,
        "invalidLoginCount": null,
        "lastInvalidLoginDate": null,
        "lockoutDate": null,
        "hasDashboard": "0",
        "passwordResetRequired": false,
        "lastPasswordChangeDate": null,
        "unverifiedEmail": null,
        "newPassword": null,
        "currentPassword": null,
        "verificationCodeIssuedDate": null,
        "verificationCode": null,
        "lastLoginAttemptIp": null,
        "authError": null,
        "inheritorOnDelete": null,
        "id": 5873,
        "tempId": null,
        "draftId": null,
        "revisionId": null,
        "uid": "f2bc2ff4-b4a4-4a77-8ac3-03997e05bd38",
        "siteSettingsId": 5873,
        "fieldLayoutId": null,
        "contentId": 2038,
        "enabled": true,
        "archived": false,
        "siteId": 1,
        "title": null,
        "slug": null,
        "uri": null,
        "dateCreated": "2019-08-29T12:53:43-07:00",
        "dateUpdated": "2019-10-30T13:40:25-07:00",
        "dateDeleted": null,
        "trashed": false,
        "propagateAll": false,
        "newSiteIds": [],
        "resaving": false,
        "duplicateOf": null,
        "previewing": false,
        "hardDelete": false,
        "ref": "tyler",
        "status": "active",
        "structureId": null,
        "url": null,
        "cooldownEndTime": null,
        "friendlyName": "Tyler",
        "fullName": "Tyler Hannan",
        "isCurrent": false,
        "name": "Tyler Hannan",
        "preferredLanguage": null,
        "remainingCooldownTime": null
    }
]